transformers_supporter/__init__.py
transformers_supporter/models/__init__.py
transformers_supporter/models/ann/__init__.py
transformers_supporter/models/ann/configuration_ann.py
transformers_supporter/models/ann/feature_extraction_ann.py
transformers_supporter/models/ann/modeling_ann.py
transformers_supporter/models/cnn/__init__.py
transformers_supporter/models/cnn/configuration_cnn.py
transformers_supporter/models/cnn/image_processing_cnn.py
transformers_supporter/models/cnn/modeling_cnn.py
transformers_supporter/models/custom_bert/__init__.py
transformers_supporter/models/custom_bert/configuration_custom_bert.py
transformers_supporter/models/custom_bert/modeling_custom_bert.py
transformers_supporter/models/embedded_1dcnn/__init__.py
transformers_supporter/models/embedded_1dcnn/configuration_embedded_1dcnn.py
transformers_supporter/models/embedded_1dcnn/modeling_embedded_1dcnn.py
transformers_supporter/models/embedded_rnn/__init__.py
transformers_supporter/models/embedded_rnn/configuration_embedded_rnn.py
transformers_supporter/models/embedded_rnn/feature_extraction_embedded_rnn.py
transformers_supporter/models/embedded_rnn/modeling_embedded_rnn.py
transformers_supporter/models/faster_rcnn/__init__.py
transformers_supporter/models/faster_rcnn/configuration_faster_rcnn.py
transformers_supporter/models/faster_rcnn/image_processing_faster_rcnn.py
transformers_supporter/models/faster_rcnn/modeling_faster_rcnn.py
transformers_supporter/models/pretrained_embedded_rnn/__init__.py
transformers_supporter/models/pretrained_embedded_rnn/configuration_pretrained_embedded_rnn.py
transformers_supporter/models/pretrained_embedded_rnn/modeling_pretrained_embedded_rnn.py
transformers_supporter/models/rnn/__init__.py
transformers_supporter/models/rnn/configuration_rnn.py
transformers_supporter/models/rnn/feature_extraction_rnn.py
transformers_supporter/models/rnn/modeling_rnn.py
transformers_supporter/pipelines/__init__.py
transformers_supporter-0.0.36.dist-info/METADATA
transformers_supporter-0.0.36.dist-info/WHEEL
transformers_supporter-0.0.36.dist-info/top_level.txt
transformers_supporter-0.0.36.dist-info/RECORD
