Metadata-Version: 2.1
Name: transformers-supporter
Version: 0.0.36
Summary: Transformers supporter
Home-page: https://github.com/automatethem/transformers-supporter
Author: Sang Ki Kwon
Author-email: automatethem@gmail.com
License: MIT
Requires-Dist: transformers
Requires-Dist: konlpy
Requires-Dist: pillow
Requires-Dist: spacy
Requires-Dist: torchtext
Requires-Dist: pytorch-supporter
